enin/__init__.py
enin/datasets.py
enin-0.0.1.dist-info/METADATA
enin-0.0.1.dist-info/WHEEL
enin-0.0.1.dist-info/licenses/LICENSE
enin-0.0.1.dist-info/RECORD
