Metadata-Version: 2.4
Name: enin
Version: 0.0.1
Summary: The official Python library for the Enin API
Project-URL: Homepage, https://enin.ai
Project-URL: Repository, https://github.com/team-enin/enin-python
Project-URL: Issues, https://github.com/team-enin/enin-python/issues
Author-email: Enin <support@enin.ai>
License: Apache-2.0
License-File: LICENSE
Classifier: License :: OSI Approved :: Apache Software License
Classifier: Operating System :: MacOS
Classifier: Operating System :: Microsoft :: Windows
Classifier: Operating System :: OS Independent
Classifier: Operating System :: POSIX
Classifier: Operating System :: POSIX :: Linux
Classifier: Programming Language :: Python :: 3.8
Classifier: Programming Language :: Python :: 3.9
Classifier: Programming Language :: Python :: 3.10
Classifier: Programming Language :: Python :: 3.11
Classifier: Programming Language :: Python :: 3.12
Classifier: Programming Language :: Python :: 3.13
Classifier: Topic :: Software Development :: Libraries :: Python Modules
Classifier: Typing :: Typed
Requires-Python: >=3.8
Requires-Dist: requests<3,>=2.32.3
